botcli/__init__.py
botcli/cli.py
botcli/generate.py
botcli-1.0.0.dist-info/AUTHORS.md
botcli-1.0.0.dist-info/LICENSE
botcli-1.0.0.dist-info/METADATA
botcli-1.0.0.dist-info/WHEEL
botcli-1.0.0.dist-info/entry_points.txt
botcli-1.0.0.dist-info/top_level.txt
botcli-1.0.0.dist-info/RECORD
