Metadata-Version: 2.1
Name: botcli
Version: 1.0.0
Summary: A cli for generating a discord.py bot structure
Home-page: https://github.com/combogangreal/BotCli
Author: Combo Gang
Author-email: contact@combogang.com
License: MIT
Classifier: Programming Language :: Python :: 3
Classifier: License :: OSI Approved :: MIT License
Classifier: Operating System :: OS Independent
License-File: LICENSE
License-File: AUTHORS.md
